enappsys/__init__.py
enappsys/client.py
enappsys/client_async.py
enappsys/credentials.py
enappsys/enum.py
enappsys/exceptions.py
enappsys/session.py
enappsys/session_async.py
enappsys/utils.py
enappsys/services/__init__.py
enappsys/services/base.py
enappsys/services/bulk.py
enappsys/services/chart.py
enappsys/services/price_volume_curve.py
enappsys/services_async/base.py
enappsys/services_async/bulk.py
enappsys/services_async/chart.py
enappsys/services_async/price_volume_curve.py
enappsys-0.1.1.dist-info/licenses/LICENSE
enappsys-0.1.1.dist-info/METADATA
enappsys-0.1.1.dist-info/WHEEL
enappsys-0.1.1.dist-info/top_level.txt
enappsys-0.1.1.dist-info/RECORD
