Metadata-Version: 2.4
Name: enappsys
Version: 0.1.1
Summary: The EnAppSys Python client provides a light-weight client that allows for simple access to EnAppSys' API services.
Author-email: Silvan Murre <silvan.murre@montel.energy>
License-Expression: MIT
Classifier: Programming Language :: Python :: 3
Classifier: Operating System :: OS Independent
Requires-Python: >=3.7
License-File: LICENSE
Requires-Dist: requests
Provides-Extra: async
Requires-Dist: aiohttp; extra == "async"
Provides-Extra: pandas
Requires-Dist: pandas; extra == "pandas"
Provides-Extra: dev
Requires-Dist: enappsys[async]; extra == "dev"
Requires-Dist: enappsys[pandas]; extra == "dev"
Requires-Dist: pre-commit; extra == "dev"
Requires-Dist: pytest-asyncio; extra == "dev"
Requires-Dist: pytest-benchmark; extra == "dev"
Requires-Dist: pytest; extra == "dev"
Requires-Dist: ruff; extra == "dev"
Dynamic: license-file
